test/__init__.py
test/test_download.py
test/test_get_data_from_tushare.py
test/test_get_trade_days_from_szex.py
tool/__init__.py
tool/download.py
tool/get_data.py
tool/common/__init__.py
tool/common/qmt_enum.py
tool/notice/__init__.py
tool/notice/sender_type.py
tool/trade_functions/__init__.py
tool/trade_functions/account.py
tool/trade_functions/current_data.py
tool/trade_functions/file_operation.py
tool/trade_functions/position.py
tool/trade_functions/stock_filters.py
tool/trade_functions/trade.py
tool/vo/__init__.py
tool/vo/qmt_obj.py
quantuaninvest_download-1.0.12.dist-info/METADATA
quantuaninvest_download-1.0.12.dist-info/WHEEL
quantuaninvest_download-1.0.12.dist-info/top_level.txt
quantuaninvest_download-1.0.12.dist-info/RECORD
