Metadata-Version: 2.1
Name: quantuaninvest-download
Version: 1.0.12
Summary: quantuan invest download schedule
Home-page: UNKNOWN
Author: jinxin
Author-email: 252992499@qq.com
License: apache 3.0
Platform: UNKNOWN
Requires: requests
